ansys/scade/pyalmgw/__init__.py
ansys/scade/pyalmgw/connector.py
ansys/scade/pyalmgw/documents.py
ansys/scade/pyalmgw/llrs.py
ansys/scade/pyalmgw/stub.py
ansys/scade/pyalmgw/utils.py
ansys/scade/pyalmgw/res/schema.xsd
ansys/scade/pyalmgw/res/stub.xml
ansys/scade/pyalmgw/res/schemas/display.json
ansys/scade/pyalmgw/res/schemas/eqsets.json
ansys/scade/pyalmgw/res/schemas/records.json
ansys/scade/pyalmgw/res/schemas/system.json
ansys/scade/pyalmgw/res/suite/element.png
ansys/scade/pyalmgw/res/suite/ifBranch.png
ansys/scade/pyalmgw/res/suite/netDiagram.png
ansys/scade/pyalmgw/res/suite/textDiagram.png
ansys/scade/pyalmgw/res/suite/whenBranch.png
ansys_scade_pyalmgw-1.1.4.dist-info/entry_points.txt
ansys_scade_pyalmgw-1.1.4.dist-info/LICENSE
ansys_scade_pyalmgw-1.1.4.dist-info/WHEEL
ansys_scade_pyalmgw-1.1.4.dist-info/METADATA
ansys_scade_pyalmgw-1.1.4.dist-info/RECORD
